__init__.py
vercel_kv.py
vercel_kv-0.1.5.dist-info/LICENSE
vercel_kv-0.1.5.dist-info/METADATA
vercel_kv-0.1.5.dist-info/WHEEL
vercel_kv-0.1.5.dist-info/top_level.txt
vercel_kv-0.1.5.dist-info/RECORD
