Metadata-Version: 2.1
Name: vercel-kv
Version: 0.1.5
Summary: https://vercel.com/docs/storage/vercel-kv/rest-api
Home-page: https://github.com/bestK/python-vercel-kv
Author: bestk
License: MIT
Classifier: License :: OSI Approved :: MIT License
Classifier: Programming Language :: Python :: 3.6
Classifier: Programming Language :: Python :: 3.7
Classifier: Programming Language :: Python :: 3.8
Classifier: Programming Language :: Python :: 3.9
License-File: LICENSE
Requires-Dist: python-dotenv ==1.0.0
Requires-Dist: requests ~=2.31.0
Requires-Dist: pydantic ~=2.1.1
Provides-Extra: dev
Requires-Dist: pytest ; extra == 'dev'
Requires-Dist: tox ; extra == 'dev'
